sparkpost/__init__.py
sparkpost/base.py
sparkpost/exceptions.py
sparkpost/metrics.py
sparkpost/recipient_lists.py
sparkpost/suppression_list.py
sparkpost/templates.py
sparkpost/transmissions.py
sparkpost/django/__init__.py
sparkpost/django/email_backend.py
sparkpost/django/exceptions.py
sparkpost/django/message.py
sparkpost/tornado/__init__.py
sparkpost/tornado/base.py
sparkpost/tornado/exceptions.py
sparkpost/tornado/transmissions.py
sparkpost/tornado/utils.py
test/__init__.py
test/test_base.py
test/test_init.py
test/test_metrics.py
test/test_recipient_lists.py
test/test_suppression_list.py
test/test_templates.py
test/test_transmissions.py
test/django/__init__.py
test/django/test_email_backend.py
test/django/test_message.py
test/django/utils.py
test/tornado/__init__.py
test/tornado/test_tornado.py
test/tornado/utils.py
sparkpost-1.3.10.dist-info/AUTHORS.rst
sparkpost-1.3.10.dist-info/LICENSE
sparkpost-1.3.10.dist-info/METADATA
sparkpost-1.3.10.dist-info/WHEEL
sparkpost-1.3.10.dist-info/top_level.txt
sparkpost-1.3.10.dist-info/RECORD
