Metadata-Version: 2.1
Name: sparkpost
Version: 1.3.10
Summary: SparkPost Python API client
Home-page: https://github.com/SparkPost/python-sparkpost
Author: SparkPost
Author-email: developers@sparkpost.com
License: Apache 2.0
Platform: UNKNOWN
Classifier: Development Status :: 5 - Production/Stable
Classifier: Intended Audience :: Developers
Classifier: Topic :: Communications :: Email
Classifier: License :: OSI Approved :: Apache Software License
Classifier: Programming Language :: Python :: 2
Classifier: Programming Language :: Python :: 2.7
Classifier: Programming Language :: Python :: 3
Classifier: Programming Language :: Python :: 3.4
Classifier: Programming Language :: Python :: 3.5
License-File: LICENSE
License-File: AUTHORS.rst
